del_ls-0.1.1.dist-info/METADATA
del_ls-0.1.1.dist-info/WHEEL
del_ls/__init__.py
del_ls/del_ls.cpython-311-darwin.so
del_ls-0.1.1.dist-info/RECORD
